Workbook

Sheet FUNCIONAMENTO
A1: NUMERO | B1: DATA | C1: CONCEPTO | D1: DEBE | E1: HABER | F1: I_G | G1: CODIGO | H1: Cod Decrip | I1: PERIODO | J1: LIBRE | K1: XUSTIFICA | L1: NOME | M1: EUROS | N1: DIA | O1: MES | P1: ANO | Q1: CHEQUE | R1: IMPRIMIR
A2: 0 | B2: 01/01/2022 | C2: SALDO ANTERIOR | E2: 64080.83 | F2: I | G2: H | H2: =VLOOKUP(G2,Codigo!$A$2:$B$46,2,FALSE) -> SALDO ANTERIOR
A3: 1 | B3: 07/01/2025 | C3: GRENKE RENT, S.L.U. | D3: 577.17 | F3: G | G3: 01 | H3: =VLOOKUP(G3,Codigo!$A$2:$B$46,2,FALSE) -> Arredamientos | I3: 1º TRIMESTRE | K3: REPROGRAFIA
A4: 2 | B4: 08/01/2025 | C4: SECURITAS DIRECT | D4: 76.54 | F4: G | G4: 02 | H4: =VLOOKUP(G4,Codigo!$A$2:$B$46,2,FALSE) -> Reparacións | I4: 1º TRIMESTRE | K4: ALARMA
A5: 3 | B5: 08/01/2025 | C5: GRENKE RENT S.L.U. | D5: 126.86 | F5: G | G5: 08 | H5: =VLOOKUP(G5,Codigo!$A$2:$B$46,2,FALSE) -> Prima de seguro | I5: 1º TRIMESTRE | K5: REPROGRAFIA
A6: 4 | B6: 06/02/2025 | C6: SECURITAS DIRECT | D6: 76.54 | F6: G | G6: 02 | H6: =VLOOKUP(G6,Codigo!$A$2:$B$46,2,FALSE) -> Reparacións | I6: 1º TRIMESTRE | K6: ALARMA
A7: 5 | B7: 13/02/2025 | C7: NEUROSINAIS | D7: 120 | F7: G | G7: 11 | H7: =VLOOKUP(G7,Codigo!$A$2:$B$46,2,FALSE) -> Gastos diversos | I7: 1º TRIMESTRE | K7: BECAS NEAE | L7: ANDREA
A8: 6 | B8: 13/02/2025 | C8: NEUROSINAIS | D8: 150 | F8: G | G8: 11 | H8: =VLOOKUP(G8,Codigo!$A$2:$B$46,2,FALSE) -> Gastos diversos | I8: 1º TRIMESTRE | K8: BECAS NEAE | L8: ROI
A9: 7 | B9: 13/02/2025 | C9: MERCACHINA | D9: 11.28 | F9: G | G9: 04.6 | H9: =VLOOKUP(G9,Codigo!$A$2:$B$46,2,FALSE) -> Outras Subministracións | I9: 1º TRIMESTRE | K9: MATERIAL
A10: 8 | B10: 26/02/2025 | C10: NEW CENTER | D10: 10.98 | F10: G | G10: 04.6 | H10: =VLOOKUP(G10,Codigo!$A$2:$B$46,2,FALSE) -> Outras Subministracións | I10: 1º TRIMESTRE
A11: 9 | B11: 26/02/2025 | C11: NEW CENTER | D11: 6.35 | F11: G | G11: 04.6 | H11: =VLOOKUP(G11,Codigo!$A$2:$B$46,2,FALSE) -> Outras Subministracións | I11: 1º TRIMESTRE
A12: 10 | B12: 26/02/2025 | C12: NEW CENTER | D12: 6 | F12: G | G12: 04.6 | H12: =VLOOKUP(G12,Codigo!$A$2:$B$46,2,FALSE) -> Outras Subministracións | I12: 1º TRIMESTRE
A13: 11 | B13: 26/02/2025 | C13: AMAZON | D13: 13.59 | F13: G | G13: 03 | H13: =VLOOKUP(G13,Codigo!$A$2:$B$46,2,FALSE) -> Material de oficina | I13: 1º TRIMESTRE
A14: 12 | B14: 26/02/2025 | C14: AMAZON | D14: 10.9 | F14: G | G14: 03 | H14: =VLOOKUP(G14,Codigo!$A$2:$B$46,2,FALSE) -> Material de oficina | I14: 1º TRIMESTRE
A15: 13 | B15: 26/02/2025 | C15: MIDETERGENTE | D15: 171.24 | F15: G | G15: 11 | H15: =VLOOKUP(G15,Codigo!$A$2:$B$46,2,FALSE) -> Gastos diversos | I15: 1º TRIMESTRE
A16: 14 | B16: 26/02/2025 | C16: A. PINILLA | D16: 375.44 | F16: G | G16: 04.6 | H16: =VLOOKUP(G16,Codigo!$A$2:$B$46,2,FALSE) -> Outras Subministracións | I16: 1º TRIMESTRE
A17: 15 | B17: 26/02/2025 | C17: ANAYA | D17: 21.33 | F17: G | G17: 04.6 | H17: =VLOOKUP(G17,Codigo!$A$2:$B$46,2,FALSE) -> Outras Subministracións | I17: 1º TRIMESTRE | K17: PLAMBE-FONDOS
A18: 16 | B18: 26/02/2025 | C18: VICENS VIVES | D18: 67.97 | F18: G | G18: 04.6 | H18: =VLOOKUP(G18,Codigo!$A$2:$B$46,2,FALSE) -> Outras Subministracións | I18: 2024 | K18: PLAMBE-FONDOS
A19: 17 | B19: 27/02/2025 | C19: ITINERANCIAS FEBREIRO PAMELA | D19: 38.58 | F19: G | G19: 10 | H19: =VLOOKUP(G19,Codigo!$A$2:$B$46,2,FALSE) -> Axudas de custo e locomoción | I19: 1º TRIMESTRE
A20: 18 | B20: 27/02/2025 | C20: ITINERANCIAS FEBREIRO CRISTINA | D20: 38.58 | F20: G | G20: 10 | H20: =VLOOKUP(G20,Codigo!$A$2:$B$46,2,FALSE) -> Axudas de custo e locomoción | I20: 1º TRIMESTRE
A21: 19 | B21: 27/02/2025 | C21: ITINERANCIAS XANEIRO PAMELA | D21: 38.58 | F21: G | G21: 10 | H21: =VLOOKUP(G21,Codigo!$A$2:$B$46,2,FALSE) -> Axudas de custo e locomoción | I21: 1º TRIMESTRE
A22: 20 | B22: 27/02/2025 | C22: ITINERANCIAS XANEIRO CRISTINA | D22: 38.58 | F22: G | G22: 10 | H22: =VLOOKUP(G22,Codigo!$A$2:$B$46,2,FALSE) -> Axudas de custo e locomoción | I22: 1º TRIMESTRE
A23: 21 | B23: 03/03/2025 | C23: CALENDARIOS ESTIÑO | E23: 123 | F23: I | G23: C | H23: =VLOOKUP(G23,Codigo!$A$2:$B$46,2,FALSE) -> Dotacións legados e subvencións | I23: 1º TRIMESTRE
A24: 22 | B24: 06/03/2025 | C24: SECURITAS DIRECT | D24: 76.54 | F24: G | G24: 02 | H24: =VLOOKUP(G24,Codigo!$A$2:$B$46,2,FALSE) -> Reparacións | I24: 1º TRIMESTRE
A25: 23 | B25: 06/03/2025 | C25: ITINERANCIAS FEBREIRO NATI | D25: 22.88 | F25: G | G25: 10 | H25: =VLOOKUP(G25,Codigo!$A$2:$B$46,2,FALSE) -> Axudas de custo e locomoción | I25: 1º TRIMESTRE
A26: 24 | B26: 06/03/2025 | C26: ITINERANCIAS XANEIRO NATI | D26: 22.88 | F26: G | G26: 10 | H26: =VLOOKUP(G26,Codigo!$A$2:$B$46,2,FALSE) -> Axudas de custo e locomoción | I26: 1º TRIMESTRE
A27: 25 | B27: 06/03/2025 | C27: ITINERANCIAS FEBREIRO BEGONA | D27: 22.88 | F27: G | G27: 10 | H27: =VLOOKUP(G27,Codigo!$A$2:$B$46,2,FALSE) -> Axudas de custo e locomoción | I27: 1º TRIMESTRE
A28: 26 | B28: 06/03/2025 | C28: ITINERANCIAS XANEIRO BEGONA | D28: 22.88 | F28: G | G28: 10 | H28: =VLOOKUP(G28,Codigo!$A$2:$B$46,2,FALSE) -> Axudas de custo e locomoción | I28: 1º TRIMESTRE
A29: 27 | B29: 06/03/2025 | C29: CALENDARIOS ESTIÑO | D29: 123 | F29: G | G29: 11 | H29: =VLOOKUP(G29,Codigo!$A$2:$B$46,2,FALSE) -> Gastos diversos | I29: 1º TRIMESTRE
A30: 28 | B30: 13/03/2025 | C30: AMAZON | D30: 28.89 | F30: G | G30: 04.6 | H30: =VLOOKUP(G30,Codigo!$A$2:$B$46,2,FALSE) -> Outras Subministracións | I30: 1º TRIMESTRE
A31: 29 | B31: 13/03/2025 | C31: E.S. GUNTIN | D31: 2866.26 | F31: G | G31: 04.1 | H31: =VLOOKUP(G31,Codigo!$A$2:$B$46,2,FALSE) -> Gasoleo | I31: 1º TRIMESTRE
A32: 30 | B32: 13/03/2025 | C32: NEUROSINAIS | D32: 90 | F32: G | G32: 11 | H32: =VLOOKUP(G32,Codigo!$A$2:$B$46,2,FALSE) -> Gastos diversos | I32: 1º TRIMESTRE | K32: BECAS NEAE | L32: ANDREA
A33: 31 | B33: 13/03/2025 | C33: NEUROSINAIS | D33: 90 | F33: G | G33: 11 | H33: =VLOOKUP(G33,Codigo!$A$2:$B$46,2,FALSE) -> Gastos diversos | I33: 1º TRIMESTRE | K33: BECAS NEAE | L33: ROI
A34: 32 | B34: 31/03/2025 | C34: BOLANDA EDICIONES | D34: 60 | F34: G | G34: 04.6 | H34: =VLOOKUP(G34,Codigo!$A$2:$B$46,2,FALSE) -> Outras Subministracións | I34: 1º TRIMESTRE | K34: PLAMBE-FONDOS
A35: 33 | B35: 31/03/2025 | C35: VIAXE-COMIDA DIRECTOR SANTIAGO 20/0 3/25 | D35: 82 | F35: G | G35: 10 | H35: =VLOOKUP(G35,Codigo!$A$2:$B$46,2,FALSE) -> Axudas de custo e locomoción | I35: 1º TRIMESTRE
A36: 34 | B36: 04/04/2025 | C36: SECURITAS DIRECT | D36: 76.54 | F36: G | G36: 02 | H36: =VLOOKUP(G36,Codigo!$A$2:$B$46,2,FALSE) -> Reparacións | I36: 2º TRIMESTRE
A37: 35 | B37: 04/04/2025 | C37: GRENKE RENT S.L.U. | D37: 577.17 | F37: G | G37: 01 | H37: =VLOOKUP(G37,Codigo!$A$2:$B$46,2,FALSE) -> Arredamientos | I37: 2º TRIMESTRE
A38: 36 | B38: 07/04/2025 | C38: DEPARTAMENTO TERRITORIAL | E38: 8648 | F38: I | G38: A1 | H38: =VLOOKUP(G38,Codigo!$A$2:$B$46,2,FALSE) -> Gastos de funcionamento | I38: 2º TRIMESTRE
A39: 37 | B39: 09/04/2025 | C39: BECA ALUMNO TRASLADADO | E39: 2226 | F39: I | G39: B | H39: =VLOOKUP(G39,Codigo!$A$2:$B$46,2,FALSE) -> Dotacións UE-Outros organismos | I39: 2º TRIMESTRE
A40: 38 | B40: 11/04/2025 | C40: NEUROSINAIS | D40: 60 | F40: G | G40: 11 | H40: =VLOOKUP(G40,Codigo!$A$2:$B$46,2,FALSE) -> Gastos diversos | I40: 1º TRIMESTRE | K40: BECAS NEAE | L40: CANDELA
A41: 39 | B41: 11/04/2025 | C41: NEUROSINAIS | D41: 90 | F41: G | G41: 11 | H41: =VLOOKUP(G41,Codigo!$A$2:$B$46,2,FALSE) -> Gastos diversos | I41: 1º TRIMESTRE | K41: BECAS NEAE | L41: ROI
A42: 40 | B42: 11/04/2025 | C42: NEUROSINAIS | D42: 120 | F42: G | G42: 11 | H42: =VLOOKUP(G42,Codigo!$A$2:$B$46,2,FALSE) -> Gastos diversos | I42: 1º TRIMESTRE | K42: BECAS NEAE | L42: ANDREA
A43: 41 | B43: 11/04/2025 | C43: MIDETERGENTE | D43: 269.95 | F43: G | G43: 11 | H43: =VLOOKUP(G43,Codigo!$A$2:$B$46,2,FALSE) -> Gastos diversos | I43: 2º TRIMESTRE
A44: 42 | B44: 11/04/2025 | C44: MARKET RAPISARDA | D44: 13.98 | F44: G | G44: 04.6 | H44: =VLOOKUP(G44,Codigo!$A$2:$B$46,2,FALSE) -> Outras Subministracións | I44: 2º TRIMESTRE
A45: 43 | B45: 23/04/2025 | C45: PRELO | D45: 15.65 | F45: G | G45: 04.6 | H45: =VLOOKUP(G45,Codigo!$A$2:$B$46,2,FALSE) -> Outras Subministracións | I45: 2º TRIMESTRE
A46: 44 | B46: 23/04/2025 | C46: SACAUNTOS | D46: 72 | F46: G | G46: 04.6 | H46: =VLOOKUP(G46,Codigo!$A$2:$B$46,2,FALSE) -> Outras Subministracións | I46: 2º TRIMESTRE | K46: PLAMBE-FONDOS
A47: 45 | B47: 23/04/2025 | C47: ITINERANCIAS CRISTINA MARZO 2025 | D47: 74.57 | F47: G | G47: 10 | H47: =VLOOKUP(G47,Codigo!$A$2:$B$46,2,FALSE) -> Axudas de custo e locomoción | I47: 2º TRIMESTRE
A48: 46 | B48: 23/04/2025 | C48: ITINERANCIAS NATI MARZO 2025 | D48: 22.88 | F48: G | G48: 10 | H48: =VLOOKUP(G48,Codigo!$A$2:$B$46,2,FALSE) -> Axudas de custo e locomoción | I48: 2º TRIMESTRE
A49: 47 | B49: 23/04/2025 | C49: ITINERANCIAS BEGONA MARZO 2025 | D49: 22.88 | F49: G | G49: 10 | H49: =VLOOKUP(G49,Codigo!$A$2:$B$46,2,FALSE) -> Axudas de custo e locomoción | I49: 2º TRIMESTRE
A50: 48 | B50: 06/05/2025 | C50: SECURITAS DIRECT | D50: 76.54 | F50: G | G50: 02 | H50: =VLOOKUP(G50,Codigo!$A$2:$B$46,2,FALSE) -> Reparacións | I50: 2º TRIMESTRE
A51: 49 | B51: 15/05/2025 | C51: GALINK | D51: 80.26 | F51: G | G51: 11 | H51: =VLOOKUP(G51,Codigo!$A$2:$B$46,2,FALSE) -> Gastos diversos | I51: 2º TRIMESTRE | K51: DESENVOLVEMENTO PROGRAMA EDUCACIÓN DIXITAL 2024
A52: 50 | B52: 15/05/2025 | C52: RESERVA AC. LUCUS AVENTURE | D52: 377 | F52: G | G52: 11 | H52: =VLOOKUP(G52,Codigo!$A$2:$B$46,2,FALSE) -> Gastos diversos | I52: 2º TRIMESTRE
A53: 51 | B53: 15/05/2025 | C53: RESERVA AC. LUCUS AVENTURE | D53: 624 | F53: G | G53: 11 | H53: =VLOOKUP(G53,Codigo!$A$2:$B$46,2,FALSE) -> Gastos diversos | I53: 2º TRIMESTRE
A54: 52 | B54: 15/05/2025 | C54: ITINERANCIAS ABRIL NATI | D54: 17.16 | F54: G | G54: 10 | H54: =VLOOKUP(G54,Codigo!$A$2:$B$46,2,FALSE) -> Axudas de custo e locomoción | I54: 2º TRIMESTRE
A55: 53 | B55: 15/05/2025 | C55: ITINERANCIAS ABRIL CRISTINA | D55: 50.08 | F55: G | G55: 10 | H55: =VLOOKUP(G55,Codigo!$A$2:$B$46,2,FALSE) -> Axudas de custo e locomoción | I55: 2º TRIMESTRE
A56: 54 | B56: 15/05/2025 | C56: ITINERANCIAS ABRIL BEGONA | D56: 17.16 | F56: G | G56: 10 | H56: =VLOOKUP(G56,Codigo!$A$2:$B$46,2,FALSE) -> Axudas de custo e locomoción | I56: 2º TRIMESTRE
A57: 55 | B57: 15/05/2025 | C57: BECA ALUMNO TRASLADADO | D57: 2226 | F57: G | G57: 11 | H57: =VLOOKUP(G57,Codigo!$A$2:$B$46,2,FALSE) -> Gastos diversos | I57: 2º TRIMESTRE
A58: 56 | B58: 15/05/2025 | C58: NEUROSINAIS | D58: 90 | F58: G | G58: 11 | H58: =VLOOKUP(G58,Codigo!$A$2:$B$46,2,FALSE) -> Gastos diversos | I58: 2º TRIMESTRE | K58: BECAS NEAE | L58: ANDREA
A59: 57 | B59: 15/05/2025 | C59: NEUROSINAIS | D59: 120 | F59: G | G59: 11 | H59: =VLOOKUP(G59,Codigo!$A$2:$B$46,2,FALSE) -> Gastos diversos | I59: 2º TRIMESTRE | K59: BECAS NEAE | L59: ROI
A60: 58 | B60: 19/05/2025 | C60: EXCUR. 5º LUCUS AVENTUR | E60: 1015 | F60: I | G60: C | H60: =VLOOKUP(G60,Codigo!$A$2:$B$46,2,FALSE) -> Dotacións legados e subvencións | I60: 2º TRIMESTRE
A61: 59 | B61: 19/05/2025 | C61: AUTOBUS 1º CICLO | E61: 308 | F61: I | G61: C | H61: =VLOOKUP(G61,Codigo!$A$2:$B$46,2,FALSE) -> Dotacións legados e subvencións | I61: 2º TRIMESTRE
A62: 60 | B62: 19/05/2025 | C62: RESERVA LUCUS AVENTUR | E62: 624 | F62: I | G62: C | H62: =VLOOKUP(G62,Codigo!$A$2:$B$46,2,FALSE) -> Dotacións legados e subvencións | I62: 2º TRIMESTRE
A63: 61 | B63: 22/05/2025 | C63: NEW CENTRE BAZAR MODA | D63: 16 | F63: G | G63: 04.6 | H63: =VLOOKUP(G63,Codigo!$A$2:$B$46,2,FALSE) -> Outras Subministracións | I63: 2º TRIMESTRE
A64: 62 | B64: 22/05/2025 | C64: NEW CENTRE BAZAR MODA | D64: 4.95 | F64: G | G64: 04.6 | H64: =VLOOKUP(G64,Codigo!$A$2:$B$46,2,FALSE) -> Outras Subministracións | I64: 2º TRIMESTRE
A65: 63 | B65: 22/05/2025 | C65: ELSUNO | D65: 1000 | F65: G | G65: 11 | H65: =VLOOKUP(G65,Codigo!$A$2:$B$46,2,FALSE) -> Gastos diversos | I65: 2º TRIMESTRE | K65: CENTROS PIE 2024
A66: 64 | B66: 27/05/2025 | C66: 2º PAGO AC. LUCUS AVENTUR | D66: 377 | F66: G | G66: 11 | H66: =VLOOKUP(G66,Codigo!$A$2:$B$46,2,FALSE) -> Gastos diversos | I66: 2º TRIMESTRE
A67: 65 | B67: 27/05/2025 | C67: LIDIA GOBERNA LAUREDA | D67: 53.65 | F67: G | G67: 04.6 | H67: =VLOOKUP(G67,Codigo!$A$2:$B$46,2,FALSE) -> Outras Subministracións | I67: 2º TRIMESTRE
A68: 66 | B68: 03/06/2025 | C68: NEUROSINAIS | D68: 120 | F68: G | G68: 11 | H68: =VLOOKUP(G68,Codigo!$A$2:$B$46,2,FALSE) -> Gastos diversos | I68: 2º TRIMESTRE | K68: BECAS NEAE | L68: ANDREA
A69: 67 | B69: 03/06/2025 | C69: NEUROSINAIS | D69: 120 | F69: G | G69: 11 | H69: =VLOOKUP(G69,Codigo!$A$2:$B$46,2,FALSE) -> Gastos diversos | I69: 2º TRIMESTRE | K69: BECAS NEAE | L69: ROI
A70: 68 | B70: 03/06/2025 | C70: 2º PAGO AC. LUCUS AVENTUR | D70: 624 | F70: G | G70: 11 | H70: =VLOOKUP(G70,Codigo!$A$2:$B$46,2,FALSE) -> Gastos diversos | I70: 2º TRIMESTRE
A71: 69 | B71: 03/06/2025 | C71: DIETA 29/05 | D71: 15 | F71: G | G71: 11 | H71: =VLOOKUP(G71,Codigo!$A$2:$B$46,2,FALSE) -> Gastos diversos | I71: 2º TRIMESTRE
A72: 70 | B72: 03/06/2025 | C72: DIETA 29/06 | D72: 15 | F72: G | G72: 11 | H72: =VLOOKUP(G72,Codigo!$A$2:$B$46,2,FALSE) -> Gastos diversos | I72: 2º TRIMESTRE
A73: 71 | B73: 03/06/2025 | C73: DIETAS 26,27,28,29/06 | D73: 60 | F73: G | G73: 11 | H73: =VLOOKUP(G73,Codigo!$A$2:$B$46,2,FALSE) -> Gastos diversos | I73: 2º TRIMESTRE
A74: 72 | B74: 03/06/2025 | C74: DIETAS 26,27,28,29/06 | D74: 60 | F74: G | G74: 11 | H74: =VLOOKUP(G74,Codigo!$A$2:$B$46,2,FALSE) -> Gastos diversos | I74: 2º TRIMESTRE
A75: 73 | B75: 03/06/2025 | C75: HERCULES EDICIONES | D75: 52 | F75: G | G75: 11 | H75: =VLOOKUP(G75,Codigo!$A$2:$B$46,2,FALSE) -> Gastos diversos | I75: 2º TRIMESTRE | K75: PLAMBE-FONDOS
A76: 74 | B76: 03/06/2025 | C76: GRAN BAZAR LIYONG | D76: 10.9 | F76: G | G76: 04.6 | H76: =VLOOKUP(G76,Codigo!$A$2:$B$46,2,FALSE) -> Outras Subministracións | I76: 2º TRIMESTRE
A77: 75 | B77: 05/06/2025 | C77: SECURITAS DIRECT | D77: 76.54 | F77: G | G77: 02 | H77: =VLOOKUP(G77,Codigo!$A$2:$B$46,2,FALSE) -> Reparacións | I77: 2º TRIMESTRE
A78: 76 | B78: 05/06/2025 | C78: 2º ABONO LUCUS AVENTUR 3º/4º | E78: 624 | F78: I | G78: C | H78: =VLOOKUP(G78,Codigo!$A$2:$B$46,2,FALSE) -> Dotacións legados e subvencións | I78: 2º TRIMESTRE
A79: 77 | B79: 05/06/2025 | C79: AUTOBUS E. INFANTIL | E79: 550 | F79: I | G79: C | H79: =VLOOKUP(G79,Codigo!$A$2:$B$46,2,FALSE) -> Dotacións legados e subvencións | I79: 2º TRIMESTRE
A80: 78 | B80: 05/06/2025 | C80: AUTOBÚS 3º/4º (BILLETES) | E80: 320 | F80: I | G80: C | H80: =VLOOKUP(G80,Codigo!$A$2:$B$46,2,FALSE) -> Dotacións legados e subvencións | I80: 2º TRIMESTRE
A81: 79 | B81: 09/06/2025 | C81: ESTURION GALICIA S.L. | D81: 1294.76 | F81: G | G81: 01 | H81: =VLOOKUP(G81,Codigo!$A$2:$B$46,2,FALSE) -> Arredamientos | I81: 2º TRIMESTRE
A82: 80 | B82: 11/06/2025 | C82: ANAYA | D82: 85.58 | F82: G | G82: 11 | H82: =VLOOKUP(G82,Codigo!$A$2:$B$46,2,FALSE) -> Gastos diversos | I82: 2º TRIMESTRE | K82: PLAMBE-FONDOS
A83: 81 | B83: 11/06/2025 | C83: ITINERANCIAS MAIO CRISTINA | D83: 66.77 | F83: G | G83: 10 | H83: =VLOOKUP(G83,Codigo!$A$2:$B$46,2,FALSE) -> Axudas de custo e locomoción | I83: 2º TRIMESTRE
A84: 82 | B84: 11/06/2025 | C84: IITINERANCIAS MAIO NATI | D84: 22.88 | F84: G | G84: 10 | H84: =VLOOKUP(G84,Codigo!$A$2:$B$46,2,FALSE) -> Axudas de custo e locomoción | I84: 2º TRIMESTRE
A85: 83 | B85: 11/06/2025 | C85: ITINERANCIAS MAIO 2025 BEGONA | D85: 22.88 | F85: G | G85: 10 | H85: =VLOOKUP(G85,Codigo!$A$2:$B$46,2,FALSE) -> Axudas de custo e locomoción | I85: 2º TRIMESTRE
A86: 84 | B86: 11/06/2025 | C86: NEX CENTER BAZAR MODA | D86: 9.25 | F86: G | G86: 04.6 | H86: =VLOOKUP(G86,Codigo!$A$2:$B$46,2,FALSE) -> Outras Subministracións | I86: 2º TRIMESTRE
A87: 85 | B87: 11/06/2025 | C87: TECNIART | D87: 437.29 | F87: G | G87: 11 | H87: =VLOOKUP(G87,Codigo!$A$2:$B$46,2,FALSE) -> Gastos diversos | I87: 2º TRIMESTRE | K87: PLAMBE-FONDOS
A88: 86 | B88: 11/06/2025 | C88: VICENS VIVES | D88: 107.82 | F88: G | G88: 11 | H88: =VLOOKUP(G88,Codigo!$A$2:$B$46,2,FALSE) -> Gastos diversos | I88: 2º TRIMESTRE | K88: PLAMBE-FONDOS
A89: 87 | B89: 11/06/2025 | C89: IRINDO | D89: 98 | F89: G | G89: 11 | H89: =VLOOKUP(G89,Codigo!$A$2:$B$46,2,FALSE) -> Gastos diversos | I89: 2º TRIMESTRE | K89: PLAMBE-FONDOS
A90: 88 | B90: 12/06/2025 | C90: AUTOBÚS 3º/4º (MOEDAS) | E90: 137 | F90: I | G90: C | H90: =VLOOKUP(G90,Codigo!$A$2:$B$46,2,FALSE) -> Dotacións legados e subvencións | I90: 2º TRIMESTRE
A91: 89 | B91: 45836 | C91: NEUROSINAIS | D91: 347.5 | F91: G | G91: 11 | H91: =VLOOKUP(G91,Codigo!$A$2:$B$46,2,FALSE) -> Gastos diversos | I91: 2º TRIMESTRE | K91: BECAS NEAE | L91: ROI
A92: 90 | B92: 12/06/2025 | C92: NEUROSINAIS | D92: 310 | F92: G | G92: 11 | H92: =VLOOKUP(G92,Codigo!$A$2:$B$46,2,FALSE) -> Gastos diversos | I92: 2º TRIMESTRE | K92: BECAS NEAE | L92: ROI
A93: 91 | B93: 45836 | C93: NEUROSINAIS | D93: 148 | F93: G | G93: 11 | H93: =VLOOKUP(G93,Codigo!$A$2:$B$46,2,FALSE) -> Gastos diversos | I93: 2º TRIMESTRE | K93: BECAS NEAE | L93: ANDREA
A94: 92 | B94: 12/06/2025 | C94: NEUROSINAIS | D94: 314.5 | F94: G | G94: 11 | H94: =VLOOKUP(G94,Codigo!$A$2:$B$46,2,FALSE) -> Gastos diversos | I94: 2º TRIMESTRE | K94: BECAS NEAE | L94: ANDREA
A95: 93 | B95: 12/06/2025 | C95: LAURA MENDEZ | D95: 557.5 | F95: G | G95: 11 | H95: =VLOOKUP(G95,Codigo!$A$2:$B$46,2,FALSE) -> Gastos diversos | I95: 2º TRIMESTRE | K95: BECAS NEAE | L95: ANDREA
A96: 94 | B96: 12/06/2025 | C96: LAURA MENDEZ | D96: 1115 | F96: G | G96: 11 | H96: =VLOOKUP(G96,Codigo!$A$2:$B$46,2,FALSE) -> Gastos diversos | I96: 2º TRIMESTRE | K96: BECAS NEAE | L96: CHRISTOPHER
A97: 95 | B97: 12/06/2025 | C97: F. BUXARDA | D97: 15.96 | F97: G | G97: 11 | H97: =VLOOKUP(G97,Codigo!$A$2:$B$46,2,FALSE) -> Gastos diversos | I97: 2º TRIMESTRE
A98: 96 | B98: 13/06/2025 | C98: DEPARTAMENTO TERRITORIAL | E98: 6486 | F98: I | G98: A1 | H98: =VLOOKUP(G98,Codigo!$A$2:$B$46,2,FALSE) -> Gastos de funcionamento | I98: 2º TRIMESTRE
A99: 97 | B99: 25/06/2025 | C99: ROSA A. FDEZ LAGAR | D99: 85 | F99: G | G99: 11 | H99: =VLOOKUP(G99,Codigo!$A$2:$B$46,2,FALSE) -> Gastos diversos | I99: 2º TRIMESTRE | K99: CENTROS PIE 2024
A100: 98 | B100: 25/06/2025 | C100: ROSA A. FDEZ LAGAR | D100: 850 | F100: G | G100: 11 | H100: =VLOOKUP(G100,Codigo!$A$2:$B$46,2,FALSE) -> Gastos diversos | I100: 2º TRIMESTRE | K100: CENTROS PIE 2024
...

Sheet DEBE
A2: I_G | B2: G
A4: CODIGO | B4: Cod Decrip | C4: PERIODO | D4: CONCEPTO | E4: DATA | F4: NUMERO | G4: DEBE | H4: Suma de DEBE
A5: 01 | B5: Arredamientos | C5: 1º TRIMESTRE | D5: GRENKE RENT, S.L.U. | E5: 07/01/2025 | F5: 1 | G5: 577.17 | H5: 577.17
C6: Total 1º TRIMESTRE | H6: 577.17
C7: 2º TRIMESTRE | D7: ESTURION GALICIA S.L. | E7: 09/06/2025 | F7: 79 | G7: 1294.76 | H7: 1294.76
D8: GRENKE RENT S.L.U. | E8: 04/04/2025 | F8: 35 | G8: 577.17 | H8: 577.17
C9: Total 2º TRIMESTRE | H9: 1871.93
C10: 3º TRIMESTRE | D10: ESTURION GALICIA S.L. | E10: 45849 | F10: 113 | G10: 287.24 | H10: 287.24
E11: 45908 | F11: 120 | G11: 263.84 | H11: 263.84
D12: GRENKE RENT S.L.U. | E12: 45849 | F12: 112 | G12: 577.17 | H12: 577.17
C13: Total 3º TRIMESTRE | H13: 1128.25
C14: 4º TRIMESTRE | D14: ESTURION GALICIA S.L. | E14: 45943 | F14: 133 | G14: 408.19 | H14: 408.19
E15: 45971 | F15: 160 | G15: 408.19 | H15: 408.19
E16: 46002 | F16: 194 | G16: 265.29 | H16: 265.29
C17: Total 4º TRIMESTRE | H17: 1081.67
A18: Total 01 | H18: 4659.02
A19: 02 | B19: Reparacións | C19: 1º TRIMESTRE | D19: SECURITAS DIRECT | E19: 06/02/2025 | F19: 4 | G19: 76.54 | H19: 76.54
E20: 06/03/2025 | F20: 22 | G20: 76.54 | H20: 76.54
E21: 08/01/2025 | F21: 2 | G21: 76.54 | H21: 76.54
C22: Total 1º TRIMESTRE | H22: 229.62
C23: 2º TRIMESTRE | D23: SECURITAS DIRECT | E23: 04/04/2025 | F23: 34 | G23: 76.54 | H23: 76.54
E24: 05/06/2025 | F24: 75 | G24: 76.54 | H24: 76.54
E25: 06/05/2025 | F25: 48 | G25: 76.54 | H25: 76.54
C26: Total 2º TRIMESTRE | H26: 229.62
C27: 3º TRIMESTRE | D27: SECURITAS DIRECT | E27: 45849 | F27: 111 | G27: 76.54 | H27: 76.54
E28: 45897 | F28: 117 | G28: 76.54 | H28: 76.54
E29: 45905 | F29: 119 | G29: 76.54 | H29: 76.54
C30: Total 3º TRIMESTRE | H30: 229.62
C31: 4º TRIMESTRE | D31: PERLADA | E31: 45975 | F31: 171 | G31: 176 | H31: 176
E32: 46021 | F32: 214 | G32: 108 | H32: 108
F33: 215 | G33: 975.5 | H33: 975.5
D34: SECURITAS DIRECT | E34: 45937 | F34: 130 | G34: 12.1 | H34: 12.1
F35: 131 | G35: 76.54 | H35: 76.54
E36: 45971 | F36: 161 | G36: 76.54 | H36: 76.54
E37: 45996 | F37: 192 | G37: 76.54 | H37: 76.54
C38: Total 4º TRIMESTRE | H38: 1501.22
A39: Total 02 | H39: 2190.08
A40: 03 | B40: Material de oficina | C40: 1º TRIMESTRE | D40: AMAZON | E40: 26/02/2025 | F40: 11 | G40: 13.59 | H40: 13.59
F41: 12 | G41: 10.9 | H41: 10.9
E42: 28/06/2025 | F42: 107 | G42: 38.24 | H42: 38.24
F43: 108 | G43: 22.99 | H43: 22.99
C44: Total 1º TRIMESTRE | H44: 85.72
C45: 3º TRIMESTRE | D45: TECNIART | E45: 45917 | F45: 125 | G45: 36.75 | H45: 36.75
C46: Total 3º TRIMESTRE | H46: 36.75
C47: 4º TRIMESTRE | D47: TECNIART | E47: 45943 | F47: 135 | G47: 88.77 | H47: 88.77
D48: Papeles Distrimar | E48: 45951 | F48: 141 | G48: 80.11 | H48: 80.11
C49: Total 4º TRIMESTRE | H49: 168.88
A50: Total 03 | H50: 291.35
A51: 04.1 | B51: Gasoleo | C51: 1º TRIMESTRE | D51: E.S. GUNTIN | E51: 13/03/2025 | F51: 29 | G51: 2866.26 | H51: 2866.26
C52: Total 1º TRIMESTRE | H52: 2866.26
C53: 3º TRIMESTRE | D53: E.S. GUNTIN | E53: 45937 | F53: 128 | G53: 3652.36 | H53: 3652.36
C54: Total 3º TRIMESTRE | H54: 3652.36
A55: Total 04.1 | H55: 6518.62
A56: 04.6 | B56: Outras Subministracións | C56: 1º TRIMESTRE | D56: A. PINILLA | E56: 26/02/2025 | F56: 14 | G56: 375.44 | H56: 375.44
D57: AMAZON | E57: 13/03/2025 | F57: 28 | G57: 28.89 | H57: 28.89
D58: ANAYA | E58: 26/02/2025 | F58: 15 | G58: 21.33 | H58: 21.33
D59: BOLANDA EDICIONES | E59: 31/03/2025 | F59: 32 | G59: 60 | H59: 60
D60: MERCACHINA | E60: 13/02/2025 | F60: 7 | G60: 11.28 | H60: 11.28
D61: NEW CENTER | E61: 26/02/2025 | F61: 8 | G61: 10.98 | H61: 10.98
F62: 9 | G62: 6.35 | H62: 6.35
F63: 10 | G63: 6 | H63: 6
C64: Total 1º TRIMESTRE | H64: 520.27
C65: 2024 | D65: VICENS VIVES | E65: 26/02/2025 | F65: 16 | G65: 67.97 | H65: 67.97
C66: Total 2024 | H66: 67.97
C67: 2º TRIMESTRE | D67: GRAN BAZAR LIYONG | E67: 03/06/2025 | F67: 74 | G67: 10.9 | H67: 10.9
D68: LIDIA GOBERNA LAUREDA | E68: 27/05/2025 | F68: 65 | G68: 53.65 | H68: 53.65
D69: MARKET RAPISARDA | E69: 11/04/2025 | F69: 42 | G69: 13.98 | H69: 13.98
D70: NEW CENTRE BAZAR MODA | E70: 22/05/2025 | F70: 61 | G70: 16 | H70: 16
F71: 62 | G71: 4.95 | H71: 4.95
D72: NEX CENTER BAZAR MODA | E72: 11/06/2025 | F72: 84 | G72: 9.25 | H72: 9.25
D73: PRELO | E73: 23/04/2025 | F73: 43 | G73: 15.65 | H73: 15.65
D74: SACAUNTOS | E74: 23/04/2025 | F74: 44 | G74: 72 | H74: 72
C75: Total 2º TRIMESTRE | H75: 196.38
C76: 3º TRIMESTRE | D76: A. PINILLA | E76: 45862 | F76: 115 | G76: 768.85 | H76: 768.85
D77: MERCACHINA | E77: 45917 | F77: 122 | G77: 17.79 | H77: 17.79
F78: 123 | G78: 16.45 | H78: 16.45
E79: 45926 | F79: 127 | G79: 16.95 | H79: 16.95
C80: Total 3º TRIMESTRE | H80: 820.04
C81: 4º TRIMESTRE | D81: GRAN BAZAR LIYONG | E81: 46003 | F81: 202 | G81: 20.9 | H81: 20.9
D82: MERCACHINA | E82: 45937 | F82: 129 | G82: 6.5 | H82: 6.5
E83: 45957 | F83: 144 | G83: 12.4 | H83: 12.4
E84: 45975 | F84: 173 | G84: 53.95 | H84: 53.95
E85: 45989 | F85: 183 | G85: 3.93 | H85: 3.93
F86: 184 | G86: 95.99 | H86: 95.99
E87: 45994 | F87: 185 | G87: 11.75 | H87: 11.75
E88: 46007 | F88: 205 | G88: 20.9 | H88: 20.9
F89: 206 | G89: 42.3 | H89: 42.3
D90: LIFE HOME | E90: 45950 | F90: 136 | G90: 72.6 | H90: 72.6
E91: 45995 | F91: 190 | G91: 30 | H91: 30
F92: 191 | G92: 50.7 | H92: 50.7
D93: FERRETERIA VAZQUEZ | E93: 45950 | F93: 137 | G93: 145.9 | H93: 145.9
D94: EM HOME | E94: 45950 | F94: 138 | G94: 8.4 | H94: 8.4
D95: TEN HOME | E95: 45957 | F95: 143 | G95: 7.22 | H95: 7.22
D96: ALDI | E96: 45972 | F96: 169 | G96: 119.97 | H96: 119.97
D97: LIDL | E97: 45972 | F97: 170 | G97: 41.22 | H97: 41.22
E98: 45994 | F98: 186 | G98: 29.94 | H98: 29.94
D99: BAZAR CHINO | E99: 46003 | F99: 203 | G99: 16.8 | H99: 16.8
D100: NIASS EL BACHIR | E100: 46008 | F100: 207 | G100: 19.3 | H100: 19.3
D101: STAR CHINA | E101: 46010 | F101: 209 | G101: 19.6 | H101: 19.6
C102: Total 4º TRIMESTRE | H102: 830.27
...

Sheet HABER
A2: I_G | B2: I
A4: CODIGO | B4: Cod Decrip | C4: PERIODO | D4: CONCEPTO | E4: DATA | F4: NUMERO | G4: HABER | H4: Suma de HABER
A5: A1 | B5: Gastos de funcionamento | C5: 2º TRIMESTRE | D5: DEPARTAMENTO TERRITORIAL | E5: 07/04/2025 | F5: 36 | G5: 8648 | H5: 8648
E6: 13/06/2025 | F6: 96 | G6: 6486 | H6: 6486
C7: Total 2º TRIMESTRE | H7: 15134
C8: 4º TRIMESTRE | D8: DEPARTAMENTO TERRITORIAL | E8: 45966 | F8: 152 | G8: 6486 | H8: 6486
E9: 46021 | F9: 210 | G9: 6558 | H9: 6558
C10: Total 4º TRIMESTRE | H10: 13044
A11: Total A1 | H11: 28178
A12: B | B12: Dotacións UE-Outros organismos | C12: 2º TRIMESTRE | D12: BECA ALUMNO TRASLADADO | E12: 09/04/2025 | F12: 37 | G12: 2226 | H12: 2226
C13: Total 2º TRIMESTRE | H13: 2226
C14: 4º TRIMESTRE | D14: BECAS S G TESORO | E14: 45966 | F14: 153 | G14: 1313 | H14: 1313
F15: 154 | G15: 400 | H15: 400
F16: 155 | G16: 2226 | H16: 2226
F17: 156 | G17: 400 | H17: 400
F18: 157 | G18: 400 | H18: 400
C19: Total 4º TRIMESTRE | H19: 4739
A20: Total B | H20: 6965
A21: C | B21: Dotacións legados e subvencións | C21: 1º TRIMESTRE | D21: CALENDARIOS ESTIÑO | E21: 03/03/2025 | F21: 21 | G21: 123 | H21: 123
C22: Total 1º TRIMESTRE | H22: 123
C23: 2º TRIMESTRE | D23: 2º ABONO LUCUS AVENTUR 3º/4º | E23: 05/06/2025 | F23: 76 | G23: 624 | H23: 624
D24: AUTOBUS 1º CICLO | E24: 19/05/2025 | F24: 59 | G24: 308 | H24: 308
D25: AUTOBÚS 3º/4º (BILLETES) | E25: 05/06/2025 | F25: 78 | G25: 320 | H25: 320
D26: AUTOBÚS 3º/4º (MOEDAS) | E26: 12/06/2025 | F26: 88 | G26: 137 | H26: 137
D27: AUTOBUS E. INFANTIL | E27: 05/06/2025 | F27: 77 | G27: 550 | H27: 550
D28: EXCUR. 5º LUCUS AVENTUR | E28: 19/05/2025 | F28: 58 | G28: 1015 | H28: 1015
D29: RESERVA LUCUS AVENTUR | E29: 19/05/2025 | F29: 60 | G29: 624 | H29: 624
C30: Total 2º TRIMESTRE | H30: 3578
C31: 4º TRIMESTRE | D31: EXCURSION GALIPARK 2º CICLO | E31: 45958 | F31: 149 | G31: 841 | H31: 841
E32: 45966 | F32: 151 | G32: 861 | H32: 861
C33: Total 4º TRIMESTRE | H33: 1702
A34: Total C | H34: 5403
A35: H | B35: SALDO ANTERIOR | D35: SALDO ANTERIOR | E35: 01/01/2022 | F35: 0 | G35: 64080.83 | H35: 64080.83
C36: Total | H36: 64080.83
A37: Total H | H37: 64080.83
A38: A3 | B38: Dotación Biblioteca | C38: 4º TRIMESTRE | D38: DEPARTAMENTO TERRITORIAL | E38: 45966 | F38: 158 | G38: 1030 | H38: 1030
C39: Total 4º TRIMESTRE | H39: 1030
A40: Total A3 | H40: 1030
A41: A2 | B41: Fondo solidario libros | C41: 4º TRIMESTRE | D41: FONDO SOLIDARIO DE LIBROS EDIXGAL | E41: 45978 | F41: 175 | G41: 4320 | H41: 4320
E42: 46055 | F42: 225 | G42: 80 | H42: 80
C43: Total 4º TRIMESTRE | H43: 4400
A44: Total A2 | H44: 4400
A45: A5 | B45: Fondos innovación | C45: 4º TRIMESTRE | D45: DEPARTAMENTO TERRITORIAL | E45: 46055 | F45: 224 | G45: 825 | H45: 825
D46: X.T CENTROS PIE 2025 | E46: 46007 | F46: 204 | G46: 1000 | H46: 1000
C47: Total 4º TRIMESTRE | H47: 1825
A48: Total A5 | H48: 1825
A49: A8 | B49: Otros | C49: 3º TRIMESTRE | D49: GRENKE RENT S.L.U. | E49: 45912 | F49: 121 | G49: 577.17 | H49: 577.17
C50: Total 3º TRIMESTRE | H50: 577.17
C51: 4º TRIMESTRE | D51: DEPARTAMENTO TERRITORIAL | E51: 46035 | F51: 223 | G51: 555 | H51: 555
C52: Total 4º TRIMESTRE | H52: 555
A53: Total A8 | H53: 1132.17
A54: Total general | H54: 113014

Sheet BALANCE
C2: BALANCE
A3: TOTAL
C4: DEBE | D4: =VLOOKUP("Total general",DEBE!A5:H1000,8,FALSE) -> 65985.68
C5: HABER | D5: =VLOOKUP("Total general",HABER!A5:H1000,8,FALSE) -> 113014
C7: RESULTADO | D7: =D5-D4 -> 47028.32

Sheet Codigo
A1: CÓDIGO | B1: DESCRIPCION
A2: 01 | B2: Arredamientos
A3: 02 | B3: Reparacións
A4: 03 | B4: Material de oficina
A5: 04 | B5: Suministracións
A6: 04.1 | B6: Gasoleo
A7: 04.2 | B7: Gas
A8: 04.3 | B8: Biomasa/Pellets
A9: 04.4 | B9: Electricidade
A10: 04.5 | B10: Auga
A11: 04.6 | B11: Outras Subministracións
A12: 05 | B12: Comunicacións
... A41: L | B41: Outros ingresos
